{
    "children": [
        {
            "id": 2,
            "text": "Antarctica",
            "isLeaf": true
        },
        {
            "id": 3,
            "text": "Bouvet Island",
            "isLeaf": true
        },
        {
            "id": 4,
            "text": "South Georgia and the South Sandwich Islands",
            "isLeaf": true
        },
        {
            "id": 5,
            "text": "Heard Island and McDonald Islands",
            "isLeaf": true
        },
        {
            "id": 6,
            "text": "French Southern Territories",
            "isLeaf": true
        }
    ],
    "id": 1,
    "text": "Antarctica"
}